dominate/__init__.py
dominate/_version.py
dominate/document.py
dominate/dom1core.py
dominate/dom_tag.py
dominate/svg.py
dominate/tags.py
dominate/util.py
dominate-2.8.0.dist-info/LICENSE.txt
dominate-2.8.0.dist-info/METADATA
dominate-2.8.0.dist-info/WHEEL
dominate-2.8.0.dist-info/top_level.txt
dominate-2.8.0.dist-info/RECORD
